{
    "m_Version": 12,
    "DisplayName": "Ballerz Shirts",
    "Icon": "Deliver",
    "Color": "FBFCFEFF",
    "IsExchange": 0,
    "InitStockPercent": 75.0,
    "Items": [
        {
            "ClassName": "BZ_Shirt_Hemp",
            "MaxPriceThreshold": 8500,
            "MinPriceThreshold": 8500,
            "SellPricePercent": 100,
            "MaxStockThreshold": 1,
            "MinStockThreshold": 1,
            "QuantityPercent": -1,
            "SpawnAttachments": [],
            "Variants": []
        },
        {
            "ClassName": "BZ_Shirt_LS",
            "MaxPriceThreshold": 8500,
            "MinPriceThreshold": 8500,
            "SellPricePercent": 100,
            "MaxStockThreshold": 1,
            "MinStockThreshold": 1,
            "QuantityPercent": -1,
            "SpawnAttachments": [],
            "Variants": []
        },
        {
            "ClassName": "BZ_Shirt_Black",
            "MaxPriceThreshold": 8500,
            "MinPriceThreshold": 8500,
            "SellPricePercent": 100,
            "MaxStockThreshold": 1,
            "MinStockThreshold": 1,
            "QuantityPercent": -1,
            "SpawnAttachments": [],
            "Variants": []
        },
        {
            "ClassName": "BZ_Shirt_Tiger",
            "MaxPriceThreshold": 8500,
            "MinPriceThreshold": 8500,
            "SellPricePercent": 100,
            "MaxStockThreshold": 1,
            "MinStockThreshold": 1,
            "QuantityPercent": -1,
            "SpawnAttachments": [],
            "Variants": []
        },
        {
            "ClassName": "BZ_Shirt_WTiger",
            "MaxPriceThreshold": 8500,
            "MinPriceThreshold": 8500,
            "SellPricePercent": 100,
            "MaxStockThreshold": 1,
            "MinStockThreshold": 1,
            "QuantityPercent": -1,
            "SpawnAttachments": [],
            "Variants": []
        },
        {
            "ClassName": "BZ_Shirt_DP",
            "MaxPriceThreshold": 8500,
            "MinPriceThreshold": 8500,
            "SellPricePercent": 100,
            "MaxStockThreshold": 1,
            "MinStockThreshold": 1,
            "QuantityPercent": -1,
            "SpawnAttachments": [],
            "Variants": []
        },
        {
            "ClassName": "BZ_Shirt_USA",
            "MaxPriceThreshold": 8500,
            "MinPriceThreshold": 8500,
            "SellPricePercent": 100,
            "MaxStockThreshold": 1,
            "MinStockThreshold": 1,
            "QuantityPercent": -1,
            "SpawnAttachments": [],
            "Variants": []
        },
        {
            "ClassName": "BZ_Shirt_LV",
            "MaxPriceThreshold": 8500,
            "MinPriceThreshold": 8500,
            "SellPricePercent": 100,
            "MaxStockThreshold": 1,
            "MinStockThreshold": 1,
            "QuantityPercent": -1,
            "SpawnAttachments": [],
            "Variants": []
        },
        {
            "ClassName": "BZ_Shirt_Gucci",
            "MaxPriceThreshold": 8500,
            "MinPriceThreshold": 8500,
            "SellPricePercent": 100,
            "MaxStockThreshold": 1,
            "MinStockThreshold": 1,
            "QuantityPercent": -1,
            "SpawnAttachments": [],
            "Variants": []
        },
        {
            "ClassName": "BZ_Shirt_Ferrari",
            "MaxPriceThreshold": 8500,
            "MinPriceThreshold": 8500,
            "SellPricePercent": 100,
            "MaxStockThreshold": 1,
            "MinStockThreshold": 1,
            "QuantityPercent": -1,
            "SpawnAttachments": [],
            "Variants": []
        },
        {
            "ClassName": "BZ_Shirt_Snake",
            "MaxPriceThreshold": 8500,
            "MinPriceThreshold": 8500,
            "SellPricePercent": 100,
            "MaxStockThreshold": 1,
            "MinStockThreshold": 1,
            "QuantityPercent": -1,
            "SpawnAttachments": [],
            "Variants": []
        },
        {
            "ClassName": "BZ_Shirt_Marvel",
            "MaxPriceThreshold": 8500,
            "MinPriceThreshold": 8500,
            "SellPricePercent": 100,
            "MaxStockThreshold": 1,
            "MinStockThreshold": 1,
            "QuantityPercent": -1,
            "SpawnAttachments": [],
            "Variants": []
        },
        {
            "ClassName": "BZ_Shirt_DC",
            "MaxPriceThreshold": 8500,
            "MinPriceThreshold": 8500,
            "SellPricePercent": 100,
            "MaxStockThreshold": 1,
            "MinStockThreshold": 1,
            "QuantityPercent": -1,
            "SpawnAttachments": [],
            "Variants": []
        },
        {
            "ClassName": "BZ_Shirt_Money",
            "MaxPriceThreshold": 8500,
            "MinPriceThreshold": 8500,
            "SellPricePercent": 100,
            "MaxStockThreshold": 1,
            "MinStockThreshold": 1,
            "QuantityPercent": -1,
            "SpawnAttachments": [],
            "Variants": []
        },
        {
            "ClassName": "BZ_Shirt_HelloKDP",
            "MaxPriceThreshold": 8500,
            "MinPriceThreshold": 8500,
            "SellPricePercent": 100,
            "MaxStockThreshold": 1,
            "MinStockThreshold": 1,
            "QuantityPercent": -1,
            "SpawnAttachments": [],
            "Variants": []
        },
        {
            "ClassName": "BZ_Shirt_TZ",
            "MaxPriceThreshold": 8500,
            "MinPriceThreshold": 8500,
            "SellPricePercent": 100,
            "MaxStockThreshold": 1,
            "MinStockThreshold": 1,
            "QuantityPercent": -1,
            "SpawnAttachments": [],
            "Variants": []
        },
        {
            "ClassName": "BZ_Shirt_HK",
            "MaxPriceThreshold": 8500,
            "MinPriceThreshold": 8500,
            "SellPricePercent": 100,
            "MaxStockThreshold": 1,
            "MinStockThreshold": 1,
            "QuantityPercent": -1,
            "SpawnAttachments": [],
            "Variants": []
        },
        {
            "ClassName": "BZ_Shirt_Cosmic",
            "MaxPriceThreshold": 8500,
            "MinPriceThreshold": 8500,
            "SellPricePercent": 100,
            "MaxStockThreshold": 1,
            "MinStockThreshold": 1,
            "QuantityPercent": -1,
            "SpawnAttachments": [],
            "Variants": []
        },
        {
            "ClassName": "BZ_Shirt_Purple",
            "MaxPriceThreshold": 8500,
            "MinPriceThreshold": 8500,
            "SellPricePercent": 100,
            "MaxStockThreshold": 1,
            "MinStockThreshold": 1,
            "QuantityPercent": -1,
            "SpawnAttachments": [],
            "Variants": []
        },
        {
            "ClassName": "BZ_Shirt_World",
            "MaxPriceThreshold": 8500,
            "MinPriceThreshold": 8500,
            "SellPricePercent": 100,
            "MaxStockThreshold": 1,
            "MinStockThreshold": 1,
            "QuantityPercent": -1,
            "SpawnAttachments": [],
            "Variants": []
        },
        {
            "ClassName": "BZ_Shirt_SMan",
            "MaxPriceThreshold": 8500,
            "MinPriceThreshold": 8500,
            "SellPricePercent": 100,
            "MaxStockThreshold": 1,
            "MinStockThreshold": 1,
            "QuantityPercent": -1,
            "SpawnAttachments": [],
            "Variants": []
        },
        {
            "ClassName": "BZ_Shirt_SW",
            "MaxPriceThreshold": 8500,
            "MinPriceThreshold": 8500,
            "SellPricePercent": 100,
            "MaxStockThreshold": 1,
            "MinStockThreshold": 1,
            "QuantityPercent": -1,
            "SpawnAttachments": [],
            "Variants": []
        },
        {
            "ClassName": "BZ_Shirt_Monster",
            "MaxPriceThreshold": 8500,
            "MinPriceThreshold": 8500,
            "SellPricePercent": 100,
            "MaxStockThreshold": 1,
            "MinStockThreshold": 1,
            "QuantityPercent": -1,
            "SpawnAttachments": [],
            "Variants": []
        },
        {
            "ClassName": "BZ_Shirt_PA",
            "MaxPriceThreshold": 8500,
            "MinPriceThreshold": 8500,
            "SellPricePercent": 100,
            "MaxStockThreshold": 1,
            "MinStockThreshold": 1,
            "QuantityPercent": -1,
            "SpawnAttachments": [],
            "Variants": []
        },
        {
            "ClassName": "BZ_Shirt_Joker",
            "MaxPriceThreshold": 8500,
            "MinPriceThreshold": 8500,
            "SellPricePercent": 100,
            "MaxStockThreshold": 1,
            "MinStockThreshold": 1,
            "QuantityPercent": -1,
            "SpawnAttachments": [],
            "Variants": []
        },
        {
            "ClassName": "BZ_Shirt_Future",
            "MaxPriceThreshold": 8500,
            "MinPriceThreshold": 8500,
            "SellPricePercent": 100,
            "MaxStockThreshold": 1,
            "MinStockThreshold": 1,
            "QuantityPercent": -1,
            "SpawnAttachments": [],
            "Variants": []
        },
        {
            "ClassName": "BZ_Shirt_Crypto",
            "MaxPriceThreshold": 8500,
            "MinPriceThreshold": 8500,
            "SellPricePercent": 100,
            "MaxStockThreshold": 1,
            "MinStockThreshold": 1,
            "QuantityPercent": -1,
            "SpawnAttachments": [],
            "Variants": []
        },
        {
            "ClassName": "BZ_Shirt_DBZ",
            "MaxPriceThreshold": 8500,
            "MinPriceThreshold": 8500,
            "SellPricePercent": 100,
            "MaxStockThreshold": 1,
            "MinStockThreshold": 1,
            "QuantityPercent": -1,
            "SpawnAttachments": [],
            "Variants": []
        },
        {
            "ClassName": "BZ_Shirt_Heineken",
            "MaxPriceThreshold": 8500,
            "MinPriceThreshold": 8500,
            "SellPricePercent": 100,
            "MaxStockThreshold": 1,
            "MinStockThreshold": 1,
            "QuantityPercent": -1,
            "SpawnAttachments": [],
            "Variants": []
        },
        {
            "ClassName": "BZ_Shirt_Gold",
            "MaxPriceThreshold": 8500,
            "MinPriceThreshold": 8500,
            "SellPricePercent": 100,
            "MaxStockThreshold": 1,
            "MinStockThreshold": 1,
            "QuantityPercent": -1,
            "SpawnAttachments": [],
            "Variants": []
        },
        {
            "ClassName": "BZ_Shirt_UCP",
            "MaxPriceThreshold": 8500,
            "MinPriceThreshold": 8500,
            "SellPricePercent": 100,
            "MaxStockThreshold": 1,
            "MinStockThreshold": 1,
            "QuantityPercent": -1,
            "SpawnAttachments": [],
            "Variants": []
        },
        {
            "ClassName": "BZ_Shirt_Tropic",
            "MaxPriceThreshold": 8500,
            "MinPriceThreshold": 8500,
            "SellPricePercent": 100,
            "MaxStockThreshold": 1,
            "MinStockThreshold": 1,
            "QuantityPercent": -1,
            "SpawnAttachments": [],
            "Variants": []
        },
        {
            "ClassName": "BZ_Shirt_Alpine",
            "MaxPriceThreshold": 8500,
            "MinPriceThreshold": 8500,
            "SellPricePercent": 100,
            "MaxStockThreshold": 1,
            "MinStockThreshold": 1,
            "QuantityPercent": -1,
            "SpawnAttachments": [],
            "Variants": []
        },
        {
            "ClassName": "BZ_Shirt_Desert",
            "MaxPriceThreshold": 8500,
            "MinPriceThreshold": 8500,
            "SellPricePercent": 100,
            "MaxStockThreshold": 1,
            "MinStockThreshold": 1,
            "QuantityPercent": -1,
            "SpawnAttachments": [],
            "Variants": []
        },
        {
            "ClassName": "BZ_Shirt_Urban",
            "MaxPriceThreshold": 8500,
            "MinPriceThreshold": 8500,
            "SellPricePercent": 100,
            "MaxStockThreshold": 1,
            "MinStockThreshold": 1,
            "QuantityPercent": -1,
            "SpawnAttachments": [],
            "Variants": []
        },
        {
            "ClassName": "BZ_Shirt_Vietnam",
            "MaxPriceThreshold": 8500,
            "MinPriceThreshold": 8500,
            "SellPricePercent": 100,
            "MaxStockThreshold": 1,
            "MinStockThreshold": 1,
            "QuantityPercent": -1,
            "SpawnAttachments": [],
            "Variants": []
        },
        {
            "ClassName": "BZ_Shirt_Phemp",
            "MaxPriceThreshold": 8500,
            "MinPriceThreshold": 8500,
            "SellPricePercent": 100,
            "MaxStockThreshold": 1,
            "MinStockThreshold": 1,
            "QuantityPercent": -1,
            "SpawnAttachments": [],
            "Variants": []
        },
        {
            "ClassName": "BZ_Shirt_CB",
            "MaxPriceThreshold": 8500,
            "MinPriceThreshold": 8500,
            "SellPricePercent": 100,
            "MaxStockThreshold": 1,
            "MinStockThreshold": 1,
            "QuantityPercent": -1,
            "SpawnAttachments": [],
            "Variants": []
        },
        {
            "ClassName": "BZ_Shirt_Anime",
            "MaxPriceThreshold": 8500,
            "MinPriceThreshold": 8500,
            "SellPricePercent": 100,
            "MaxStockThreshold": 1,
            "MinStockThreshold": 1,
            "QuantityPercent": -1,
            "SpawnAttachments": [],
            "Variants": []
        },
        {
            "ClassName": "BZ_Shirt_Scooby",
            "MaxPriceThreshold": 8500,
            "MinPriceThreshold": 8500,
            "SellPricePercent": 100,
            "MaxStockThreshold": 1,
            "MinStockThreshold": 1,
            "QuantityPercent": -1,
            "SpawnAttachments": [],
            "Variants": []
        },
		{
            "ClassName": "BZ_Shirt_Abstract1",
            "MaxPriceThreshold": 8500,
            "MinPriceThreshold": 8500,
            "SellPricePercent": 100,
            "MaxStockThreshold": 1,
            "MinStockThreshold": 1,
            "QuantityPercent": -1,
            "SpawnAttachments": [],
            "Variants": []
        },
		{
            "ClassName": "BZ_Shirt_Abstract2",
            "MaxPriceThreshold": 8500,
            "MinPriceThreshold": 8500,
            "SellPricePercent": 100,
            "MaxStockThreshold": 1,
            "MinStockThreshold": 1,
            "QuantityPercent": -1,
            "SpawnAttachments": [],
            "Variants": []
        },

        {
            "ClassName": "BZ_Shirt_Alien",
            "MaxPriceThreshold": 8500,
            "MinPriceThreshold": 8500,
            "SellPricePercent": 100,
            "MaxStockThreshold": 1,
            "MinStockThreshold": 1,
            "QuantityPercent": -1,
            "SpawnAttachments": [],
            "Variants": []
        },
        {
            "ClassName": "BZ_Shirt_AlienWare",
            "MaxPriceThreshold": 8500,
            "MinPriceThreshold": 8500,
            "SellPricePercent": 100,
            "MaxStockThreshold": 1,
            "MinStockThreshold": 1,
            "QuantityPercent": -1,
            "SpawnAttachments": [],
            "Variants": []
        },
        {
            "ClassName": "BZ_Shirt_AquaCamo",
            "MaxPriceThreshold": 8500,
            "MinPriceThreshold": 8500,
            "SellPricePercent": 100,
            "MaxStockThreshold": 1,
            "MinStockThreshold": 1,
            "QuantityPercent": -1,
            "SpawnAttachments": [],
            "Variants": []
        },
        {
            "ClassName": "BZ_Shirt_AquaHemp",
            "MaxPriceThreshold": 8500,
            "MinPriceThreshold": 8500,
            "SellPricePercent": 100,
            "MaxStockThreshold": 1,
            "MinStockThreshold": 1,
            "QuantityPercent": -1,
            "SpawnAttachments": [],
            "Variants": []
        },
        {
            "ClassName": "BZ_Shirt_Bananas",
            "MaxPriceThreshold": 8500,
            "MinPriceThreshold": 8500,
            "SellPricePercent": 100,
            "MaxStockThreshold": 1,
            "MinStockThreshold": 1,
            "QuantityPercent": -1,
            "SpawnAttachments": [],
            "Variants": []
        },
        {
            "ClassName": "BZ_Shirt_Bee",
            "MaxPriceThreshold": 8500,
            "MinPriceThreshold": 8500,
            "SellPricePercent": 100,
            "MaxStockThreshold": 1,
            "MinStockThreshold": 1,
            "QuantityPercent": -1,
            "SpawnAttachments": [],
            "Variants": []
        },
        {
            "ClassName": "BZ_Shirt_Beetlejuice",
            "MaxPriceThreshold": 8500,
            "MinPriceThreshold": 8500,
            "SellPricePercent": 100,
            "MaxStockThreshold": 1,
            "MinStockThreshold": 1,
            "QuantityPercent": -1,
            "SpawnAttachments": [],
            "Variants": []
        },
        {
            "ClassName": "BZ_Shirt_BlueHemp",
            "MaxPriceThreshold": 8500,
            "MinPriceThreshold": 8500,
            "SellPricePercent": 100,
            "MaxStockThreshold": 1,
            "MinStockThreshold": 1,
            "QuantityPercent": -1,
            "SpawnAttachments": [],
            "Variants": []
        },
        {
            "ClassName": "BZ_Shirt_Bubbles",
            "MaxPriceThreshold": 8500,
            "MinPriceThreshold": 8500,
            "SellPricePercent": 100,
            "MaxStockThreshold": 1,
            "MinStockThreshold": 1,
            "QuantityPercent": -1,
            "SpawnAttachments": [],
            "Variants": []
        },
        {
            "ClassName": "BZ_Shirt_Budweiser",
            "MaxPriceThreshold": 8500,
            "MinPriceThreshold": 8500,
            "SellPricePercent": 100,
            "MaxStockThreshold": 1,
            "MinStockThreshold": 1,
            "QuantityPercent": -1,
            "SpawnAttachments": [],
            "Variants": []
        },
        {
            "ClassName": "BZ_Shirt_Circuit",
            "MaxPriceThreshold": 8500,
            "MinPriceThreshold": 8500,
            "SellPricePercent": 100,
            "MaxStockThreshold": 1,
            "MinStockThreshold": 1,
            "QuantityPercent": -1,
            "SpawnAttachments": [],
            "Variants": []
        },
        {
            "ClassName": "BZ_Shirt_CocaCola",
            "MaxPriceThreshold": 8500,
            "MinPriceThreshold": 8500,
            "SellPricePercent": 100,
            "MaxStockThreshold": 1,
            "MinStockThreshold": 1,
            "QuantityPercent": -1,
            "SpawnAttachments": [],
            "Variants": []
        },
        {
            "ClassName": "BZ_Shirt_CrocHide",
            "MaxPriceThreshold": 8500,
            "MinPriceThreshold": 8500,
            "SellPricePercent": 100,
            "MaxStockThreshold": 1,
            "MinStockThreshold": 1,
            "QuantityPercent": -1,
            "SpawnAttachments": [],
            "Variants": []
        },
        {
            "ClassName": "BZ_Shirt_DeathNote",
            "MaxPriceThreshold": 8500,
            "MinPriceThreshold": 8500,
            "SellPricePercent": 100,
            "MaxStockThreshold": 1,
            "MinStockThreshold": 1,
            "QuantityPercent": -1,
            "SpawnAttachments": [],
            "Variants": []
        },
        {
            "ClassName": "BZ_Shirt_DemonSlayer",
            "MaxPriceThreshold": 8500,
            "MinPriceThreshold": 8500,
            "SellPricePercent": 100,
            "MaxStockThreshold": 1,
            "MinStockThreshold": 1,
            "QuantityPercent": -1,
            "SpawnAttachments": [],
            "Variants": []
        },
        {
            "ClassName": "BZ_Shirt_Glitter",
            "MaxPriceThreshold": 8500,
            "MinPriceThreshold": 8500,
            "SellPricePercent": 100,
            "MaxStockThreshold": 1,
            "MinStockThreshold": 1,
            "QuantityPercent": -1,
            "SpawnAttachments": [],
            "Variants": []
        },
        {
            "ClassName": "BZ_Shirt_Haribo",
            "MaxPriceThreshold": 8500,
            "MinPriceThreshold": 8500,
            "SellPricePercent": 100,
            "MaxStockThreshold": 1,
            "MinStockThreshold": 1,
            "QuantityPercent": -1,
            "SpawnAttachments": [],
            "Variants": []
        },
        {
            "ClassName": "BZ_Shirt_Hex1",
            "MaxPriceThreshold": 8500,
            "MinPriceThreshold": 8500,
            "SellPricePercent": 100,
            "MaxStockThreshold": 1,
            "MinStockThreshold": 1,
            "QuantityPercent": -1,
            "SpawnAttachments": [],
            "Variants": []
        },
        {
            "ClassName": "BZ_Shirt_Hex2",
            "MaxPriceThreshold": 8500,
            "MinPriceThreshold": 8500,
            "SellPricePercent": 100,
            "MaxStockThreshold": 1,
            "MinStockThreshold": 1,
            "QuantityPercent": -1,
            "SpawnAttachments": [],
            "Variants": []
        },
        {
            "ClassName": "BZ_Shirt_Hex3",
            "MaxPriceThreshold": 8500,
            "MinPriceThreshold": 8500,
            "SellPricePercent": 100,
            "MaxStockThreshold": 1,
            "MinStockThreshold": 1,
            "QuantityPercent": -1,
            "SpawnAttachments": [],
            "Variants": []
        },
        {
            "ClassName": "BZ_Shirt_Lava",
            "MaxPriceThreshold": 8500,
            "MinPriceThreshold": 8500,
            "SellPricePercent": 100,
            "MaxStockThreshold": 1,
            "MinStockThreshold": 1,
            "QuantityPercent": -1,
            "SpawnAttachments": [],
            "Variants": []
        },
        {
            "ClassName": "BZ_Shirt_Math",
            "MaxPriceThreshold": 8500,
            "MinPriceThreshold": 8500,
            "SellPricePercent": 100,
            "MaxStockThreshold": 1,
            "MinStockThreshold": 1,
            "QuantityPercent": -1,
            "SpawnAttachments": [],
            "Variants": []
        },
        {
            "ClassName": "BZ_Shirt_Matrix",
            "MaxPriceThreshold": 8500,
            "MinPriceThreshold": 8500,
            "SellPricePercent": 100,
            "MaxStockThreshold": 1,
            "MinStockThreshold": 1,
            "QuantityPercent": -1,
            "SpawnAttachments": [],
            "Variants": []
        },
        {
            "ClassName": "BZ_Shirt_MountainDew",
            "MaxPriceThreshold": 8500,
            "MinPriceThreshold": 8500,
            "SellPricePercent": 100,
            "MaxStockThreshold": 1,
            "MinStockThreshold": 1,
            "QuantityPercent": -1,
            "SpawnAttachments": [],
            "Variants": []
        },
        {
            "ClassName": "BZ_Shirt_OrangeHemp",
            "MaxPriceThreshold": 8500,
            "MinPriceThreshold": 8500,
            "SellPricePercent": 100,
            "MaxStockThreshold": 1,
            "MinStockThreshold": 1,
            "QuantityPercent": -1,
            "SpawnAttachments": [],
            "Variants": []
        },
        {
            "ClassName": "BZ_Shirt_Pepsi",
            "MaxPriceThreshold": 8500,
            "MinPriceThreshold": 8500,
            "SellPricePercent": 100,
            "MaxStockThreshold": 1,
            "MinStockThreshold": 1,
            "QuantityPercent": -1,
            "SpawnAttachments": [],
            "Variants": []
        },
        {
            "ClassName": "BZ_Shirt_PinkHemp",
            "MaxPriceThreshold": 8500,
            "MinPriceThreshold": 8500,
            "SellPricePercent": 100,
            "MaxStockThreshold": 1,
            "MinStockThreshold": 1,
            "QuantityPercent": -1,
            "SpawnAttachments": [],
            "Variants": []
        },
        {
            "ClassName": "BZ_Shirt_PokeMon",
            "MaxPriceThreshold": 8500,
            "MinPriceThreshold": 8500,
            "SellPricePercent": 100,
            "MaxStockThreshold": 1,
            "MinStockThreshold": 1,
            "QuantityPercent": -1,
            "SpawnAttachments": [],
            "Variants": []
        },
        {
            "ClassName": "BZ_Shirt_Razor",
            "MaxPriceThreshold": 8500,
            "MinPriceThreshold": 8500,
            "SellPricePercent": 100,
            "MaxStockThreshold": 1,
            "MinStockThreshold": 1,
            "QuantityPercent": -1,
            "SpawnAttachments": [],
            "Variants": []
        },
        {
            "ClassName": "BZ_Shirt_RedCamo",
            "MaxPriceThreshold": 8500,
            "MinPriceThreshold": 8500,
            "SellPricePercent": 100,
            "MaxStockThreshold": 1,
            "MinStockThreshold": 1,
            "QuantityPercent": -1,
            "SpawnAttachments": [],
            "Variants": []
        },
        {
            "ClassName": "BZ_Shirt_RedHemp",
            "MaxPriceThreshold": 8500,
            "MinPriceThreshold": 8500,
            "SellPricePercent": 100,
            "MaxStockThreshold": 1,
            "MinStockThreshold": 1,
            "QuantityPercent": -1,
            "SpawnAttachments": [],
            "Variants": []
        },
        {
            "ClassName": "BZ_Shirt_RickandMorty",
            "MaxPriceThreshold": 8500,
            "MinPriceThreshold": 8500,
            "SellPricePercent": 100,
            "MaxStockThreshold": 1,
            "MinStockThreshold": 1,
            "QuantityPercent": -1,
            "SpawnAttachments": [],
            "Variants": []
        },
        {
            "ClassName": "BZ_Shirt_Simpsons",
            "MaxPriceThreshold": 8500,
            "MinPriceThreshold": 8500,
            "SellPricePercent": 100,
            "MaxStockThreshold": 1,
            "MinStockThreshold": 1,
            "QuantityPercent": -1,
            "SpawnAttachments": [],
            "Variants": []
        },
        {
            "ClassName": "BZ_Shirt_Spongebob",
            "MaxPriceThreshold": 8500,
            "MinPriceThreshold": 8500,
            "SellPricePercent": 100,
            "MaxStockThreshold": 1,
            "MinStockThreshold": 1,
            "QuantityPercent": -1,
            "SpawnAttachments": [],
            "Variants": []
        },
        {
            "ClassName": "BZ_Shirt_StrangerThings",
            "MaxPriceThreshold": 8500,
            "MinPriceThreshold": 8500,
            "SellPricePercent": 100,
            "MaxStockThreshold": 1,
            "MinStockThreshold": 1,
            "QuantityPercent": -1,
            "SpawnAttachments": [],
            "Variants": []
        },
        {
            "ClassName": "BZ_Shirt_Thai",
            "MaxPriceThreshold": 8500,
            "MinPriceThreshold": 8500,
            "SellPricePercent": 100,
            "MaxStockThreshold": 1,
            "MinStockThreshold": 1,
            "QuantityPercent": -1,
            "SpawnAttachments": [],
            "Variants": []
        },
        {
            "ClassName": "BZ_Shirt_YellowHemp",
            "MaxPriceThreshold": 8500,
            "MinPriceThreshold": 8500,
            "SellPricePercent": 100,
            "MaxStockThreshold": 1,
            "MinStockThreshold": 1,
            "QuantityPercent": -1,
            "SpawnAttachments": [],
            "Variants": []
        },
        {
            "ClassName": "BZ_Shirt_Woodland",
            "MaxPriceThreshold": 8500,
            "MinPriceThreshold": 8500,
            "SellPricePercent": 100,
            "MaxStockThreshold": 1,
            "MinStockThreshold": 1,
            "QuantityPercent": -1,
            "SpawnAttachments": [],
            "Variants": []
        }

    ]
}